nlrest/__init__.py
nlrest/cli.py
nlrest-0.1.3.dist-info/METADATA
nlrest-0.1.3.dist-info/WHEEL
nlrest-0.1.3.dist-info/entry_points.txt
nlrest-0.1.3.dist-info/top_level.txt
nlrest-0.1.3.dist-info/RECORD
