Metadata-Version: 2.1
Name: nlrest
Version: 0.1.3
Summary: A CLI tool to convert natural language to REST API queries.
Home-page: https://github.com/yourusername/nlrest
Author: TheTrueShell
Author-email: thetrueshell@tinymail.uk
Requires-Python: >=3.6
Requires-Dist: openai
Requires-Dist: requests
